{"backend": "tfidf", "sbert_model_name": null, "code_projector": {"dim": 384, "max_features": 8192, "prefix": "code", "vocab": {"lines": 0, "-": 1, ";": 2, "code": 3, "ts": 4, "{": 5, "}": 6, "class": 7, "name": 8, "signature": 9, "symbol": 10, "path": 11, "extension": 12, ":": 13, ".": 14, ")": 15, "(": 16, "const": 17, ",": 18, ">": 19, "string": 20, "/": 21, "function": 22, "text": 23, "for": 24, "line": 25, "if": 26, "server": 27, "the": 28, "to": 29, "channel": 30, "output": 31, "and": 32, "create": 33, "local": 34, "graph": 35, "append": 36, "null": 37, "so": 38, "it": 39, "vscode": 40, "md": 41, "number": 42, "appendline": 43, "codemd": 44, "||": 45, "click": 46, "catch": 47, "err": 48, "on": 49, "is": 50, "message": 51, "new": 52, "status": 53, "stop": 54, "outputchannel": 55, "callgraph": 56, "return": 57, "url": 58, "==": 59, "html": 60, "full": 61, "result": 62, "a": 63, "search": 64, "this": 65, "file": 66, "only": 67, "extensioncontext": 68, "item": 69, "push": 70, "any": 71, "stopserver": 72, "before": 73, "already": 74, "in": 75, "codemdgraphs": 76, "by": 77, "true": 78, "an": 79, "webview": 80, "no": 81, "graphs": 82, "changes": 83, "open": 84, "change": 85, "context": 86, "workspace": 87, "actually": 88, "false": 89, "check": 90, "run": 91, "get": 92, "analysis": 93, "!=": 94, "set": 95, "out": 96, "yet": 97, "json": 98, "start": 99, "await": 100, "not": 101, "try": 102, "async": 103, "+": 104, "at": 105, "of": 106, "&&": 107, "0": 108, "element": 109, "]": 110, "specific": 111, "label": 112, "fullname": 113, "else": 114, "can": 115, "content": 116, "artifact": 117, "<": 118, "interface": 119, "[": 120, "graphsymbol": 121, "last": 122, "post": 123, "type": 124, "editor": 125, "tooltip": 126, "never": 127, "folders": 128, "then": 129, "openeditorpanel": 130, "reveal": 131, "stale": 132, "port": 133, "provider": 134, "write": 135, "needed": 136, "show": 137, "export": 138, "command": 139, "graphsviewprovider": 140, "view": 141, "length": 142, "getconfiguration": 143, "kill": 144, "time": 145, "subscriptions": 146, "100": 147, "startup": 148, "initial": 149, "mcp": 150, "commands": 151, "statusbaritem": 152, "8100": 153, "background": 154, "configuration": 155, "workspacefolders": 156, "window": 157, "bar": 158, "runstartupchangescheck": 159, "panel": 160, "generate": 161, "config": 162, "ready": 163, "resolve": 164, "error": 165, "configured": 166, "exitcode": 167, "proc": 168, "date": 169, "ms": 170, "base": 171, "fetch": 172, "waiting": 173, "make": 174, "baseurl": 175, "exit": 176, "n": 177, "tracked": 178, "add": 179, "js": 180, "always": 181, "uri": 182, "dir": 183, "commits": 184, "outdiruri": 185, "parse": 186, "repairmirroredartifactsforwebview": 187, "generated": 188, "mirrored": 189, "joinpath": 190, "exists": 191, "g": 192, "or": 193, "existssync": 194, "e": 195, "spawnsync": 196, "would": 197, "fs": 198, "anything": 199, "effort": 200, "later": 201, "rev": 202, "source": 203, "than": 204, "void": 205, "snippet": 206, "utf8": 207, "what": 208, "entry": 209, "git": 210, "backend": 211, "well": 212, "that": 213, "2494": 214, "build": 215, "be": 216, "as": 217, "stdout": 218, "changed": 219, "artifacts": 220, "same": 221, "spawn": 222, "earlier": 223, "normalizedsearchresult": 224, "found": 225, "sync": 226, "are": 227, "first": 228, "from": 229, "*": 230, "1": 231, "static": 232, "cytoscape": 233, "otherwise": 234, "updated": 235, "index": 236, "instead": 237, "node": 238, "relative": 239, "promise": 240, "t": 241, "default": 242, "per": 243, "over": 244, "repair": 245, "head": 246, "skipped": 247, "we": 248, "which": 249, "key": 250, "current": 251, "s": 252, "rather": 253, "encoding": 254, "preferred": 255, "query": 256, "has": 257, "normalized": 258, "when": 259, "candidate": 260, "dev": 261, "without": 262, "join": 263, "mirror": 264, "every": 265, "since": 266, "cwd": 267, "folder": 268, "best": 269, "wide": 270, "artifactentry": 271, "doesn": 272, "just": 273, "localcallgraphindex": 274, "commit": 275, "read": 276, "state": 277, "fspath": 278, "focus": 279, "min": 280, "repo": 281, "readfilesync": 282, "updatedat": 283, "showing": 284, "trim": 285, "artifact_output_dir": 286, "subgraph": 287, "laststatus": 288, "render": 289, "results": 290, "document": 291, "escape": 292, "inner": 293, "textcontent": 294, "escapehtml": 295, "createelement": 296, "innerhtml": 297, "div": 298, "openeditor": 299, "they": 300, "killstaleserveronport": 301, "circle": 302, "registercommand": 303, "discover": 304, "setupprojectmcpconfigs": 305, "configs": 306, "kick": 307, "statusbaralignment": 308, "setup": 309, "there": 310, "manual": 311, "rungenerate": 312, "prepared": 313, "register": 314, "startupanalysis": 315, "activity": 316, "itself": 317, "unprompted": 318, "createoutputchannel": 319, "icon": 320, "autoreveal": 321, "outline": 322, "unless": 323, "activate": 324, "codemdlocal": 325, "previously": 326, "registerwebviewviewprovider": 327, "setupmcp": 328, "failed": 329, "createstatusbaritem": 330, "appeared": 331, "user": 332, "waited": 333, "334": 334, "project": 335, "auto": 336, "397": 337, "alignment": 338, "surface": 339, "autowriteprojectmcpconfig": 340, "off": 341, "look": 342, "opens": 343, "quiet": 344, "left": 345, "knew": 346, "registermcpprovider": 347, "deactivate": 348, "401": 349, "399": 350, "timeoutms": 351, "sure": 352, "api": 353, "755": 354, "fastapi": 355, "installed": 356, "750": 357, "731": 358, "txt": 359, "res": 360, "became": 361, "settimeout": 362, "exited": 363, "ok": 364, "openapi": 365, "timeout": 366, "now": 367, "timed": 368, "reject": 369, "accepting": 370, "pythonpath": 371, "fast": 372, "requirements": 373, "python": 374, "connections": 375, "tree": 376, "process": 377, "size": 378, "serverprocess": 379, "processes": 380, "clear": 381, "killprocesstree": 382, "771": 383, "es": 384, "stopping": 385, "trackedprocesses": 386, "760": 387, "pid": 388, "degree": 389, "root": 390, "nodeelement": 391, "route": 392, "fan": 393, "absolute": 394, "startswith": 395, "replace": 396, "tolowercase": 397, "idx": 398, "array": 399, "mains": 400, "excluding": 401, "handlers": 402, "copied": 403, "lib": 404, "entries": 405, "better": 406, "even": 407, "copy": 408, "shouldmirrorartifact": 409, "readfile": 410, "analyze": 411, "isostring": 412, "been": 413, "edge": 414, "35": 415, "identified": 416, "explicitelements": 417, ">=": 418, "parenturi": 419, "flowelementsfor": 420, "collectartifacturls": 421, "parts": 422, "target": 423, "12": 424, "marker": 425, "limit": 426, "more": 427, "toisostring": 428, "obj": 429, "curated": 430, "often": 431, "safeworkspacecopy": 432, "overwriting": 433, "codemdurl": 434, "75": 435, "tends": 436, "searchlocalcallgraph": 437, "stays": 438, "repo_id": 439, "compute": 440, "sourcepath": 441, "foo": 442, "stat": 443, "blanks": 444, "gitstatehash": 445, "statsync": 446, "all": 447, "lowernode": 448, "readstoredgitstatehash": 449, "proxy": 450, "suffix": 451, "lowerquery": 452, "tell": 453, "mtimems": 454, "stripped": 455, "tail": 456, "boolean": 457, "initialelements": 458, "explicit": 459, "score": 460, "should": 461, "data": 462, "sourcemtimems": 463, "htmluri": 464, "treat": 465, "depth": 466, "2": 467, "higher": 468, "b": 469, "analyzelocalpath": 470, "thousands": 471, "location": 472, "rewrite": 473, "meaningful": 474, "value": 475, "scorelocalcallgraphmatch": 476, "runs": 477, "module": 478, "htmlrelativeprefix": 479, "etc": 480, "upload": 481, "compare": 482, "flow": 483, "rel": 484, "raw": 485, "locale": 486, "cheap": 487, "localecompare": 488, "some": 489, "slice": 490, "nested": 491, "50": 492, "map": 493, "match": 494, "workspaceroot": 495, "function_files": 496, "mechanism": 497, "split": 498, "entry_points": 499, "stored": 500, "object": 501, "report": 502, "original": 503, "statustext": 504, "untracked": 505, "skip": 506, "normalizes": 507, "sort": 508, "local_search_function_file_candidates": 509, "tostring": 510, "incidental": 511, "lower": 512, "crypto": 513, "slash": 514, "id": 515, "next": 516, "webview_support_artifacts": 517, "with": 518, "createhash": 519, "plus": 520, "case": 521, "extensionuri": 522, "convention": 523, "prefix": 524, "renderer": 525, "nodes": 526, "our": 527, "artifacturlprefix": 528, "copyifexists": 529, "supportprefix": 530, "relpath": 531, "serverurl": 532, "porcelain": 533, "highest": 534, "60": 535, "other": 536, "uploadresult": 537, "writestoredgitstatehash": 538, "lastindexof": 539, "correct": 540, "workspacename": 541, "machine": 542, "nodelabels": 543, "callers": 544, "parent": 545, "hand": 546, "single": 547, "labels": 548, "bare": 549, "safeworkspacecreatedirectory": 550, "rewritten": 551, "segments": 552, "segment": 553, "node_labels": 554, "place": 555, "elements": 556, "functionfiles": 557, "lastslash": 558, "safe": 559, "analysis_state_file": 560, "continue": 561, "leading": 562, "pop": 563, "hex": 564, "edges": 565, "download": 566, "firstroot": 567, "seen": 568, "repeat": 569, "like": 570, "urls": 571, "actual": 572, "analyzer": 573, "fail": 574, "exact": 575, "sha256": 576, "emitted": 577, "filename": 578, "collect": 579, "mtime": 580, "returns": 581, "buildfilebynodeindex": 582, "850": 583, "bundled": 584, "entrypoints": 585, "computegitstatehash": 586, "matches": 587, "was": 588, "candidates": 589, "real": 590, "package": 591, "dotted": 592, "downloadartifacts": 593, "fetchbuffer": 594, "85": 595, "response": 596, "own": 597, "support": 598, "developer": 599, "want": 600, "isn": 601, "demo": 602, "sensible": 603, "hub": 604, "lowerlabel": 605, "un": 606, "let": 607, "outdirfspath": 608, "points": 609, "repoid": 610, "generator": 611, "includes": 612, "hash": 613, "stringify": 614, "names": 615, "typeof": 616, "filebynode": 617, "16": 618, "files": 619, "connected": 620, "crashes": 621, "indexof": 622, "main": 623, "mirrored_html_artifacts": 624, "directory": 625, "digest": 626, "used": 627, "generic": 628, "cli": 629, "don": 630, "loadlocalcallgraphindex": 631, "safeworkspacewritefile": 632, "buffer": 633, "isarray": 634, "rewritehtmlartifactforwebview": 635, "extensions": 636, "load": 637, "pick": 638, "update": 639, "two": 640, "folderpath": 641, "means": 642, "whatever": 643, "starts": 644, "record": 645, "local_search_graph_candidates": 646, "1098": 647, "1095": 648, "changetime": 649, "identifying": 650, "fields": 651, "through": 652, "carried": 653, "1328": 654, "centered": 655, "ask": 656, "1316": 657, "navigatable": 658, "implements": 659, "up": 660, "made": 661, "localresourceroots": 662, "enablescripts": 663, "resolvewebviewview": 664, "empty": 665, "ondidreceivemessage": 666, "handle": 667, "localgraphfileuri": 668, "csp": 669, "running": 670, "sidebar": 671, "reponame": 672, "webviewviewprovider": 673, "finish": 674, "handed": 675, "ensurelocalgraphloaded": 676, "mid": 677, "pattern": 678, "relativepattern": 679, "displayed": 680, "changesbusy": 681, "column": 682, "createfilesystemwatcher": 683, "may": 684, "sessionstartgitref": 685, "session": 686, "unchanged": 687, "owner_name": 688, "disposable": 689, "recomputed": 690, "localsearchindex": 691, "started": 692, "watcher": 693, "filesystemwatcher": 694, "script": 695, "display": 696, "back": 697, "iframe": 698, "retain": 699, "usable": 700, "gets": 701, "ensure": 702, "active": 703, "existing": 704, "ref": 705, "mcp_usage_file": 706, "src": 707, "captured": 708, "webviewview": 709, "readonly": 710, "sidepanelready": 711, "posting": 712, "localgraphreadypromise": 713, "usage": 714, "handlemessage": 715, "renders": 716, "hidden": 717, "right": 718, "runchangescheck": 719, "ownername": 720, "regenerate": 721, "history": 722, "resolvegraphurlforwebview": 723, "undefined": 724, "lastdisplayedservergraphurl": 725, "postdisplayedgraph": 726, "performed": 727, "side": 728, "commitsbusy": 729, "rewrites": 730, "fresh": 731, "ondidchange": 732, "displayedgraphfileuri": 733, "i": 734, "dispose": 735, "point": 736, "ever": 737, "repo_name": 738, "owner": 739, "comparison": 740, "clients": 741, "showinformationmessage": 742, "total": 743, "away": 744, "constructor": 745, "op": 746, "needing": 747, "repairs": 748, "createwebviewpanel": 749, "clearing": 750, "focuslatestchange": 751, "delete": 752, "ensuremcpusagewatcher": 753, "startupchangescheckstarted": 754, "move": 755, "resultpath": 756, "finished": 757, "opengraphpanel": 758, "must": 759, "latest": 760, "being": 761, "totalcalls": 762, "previous": 763, "retaincontextwhenhidden": 764, "viewready": 765, "workspacefolder": 766, "ondidcreate": 767, "adopted": 768, "enable": 769, "mcpusagewatcher": 770, "messagedisposable": 771, "its": 772, "sitting": 773, "focused": 774, "wins": 775, "meaning": 776, "postgraph": 777, "hasgenerated": 778, "adopt": 779, "blank": 780, "cover": 781, "rendered": 782, "rewriting": 783, "nothing": 784, "refresh": 785, "information": 786, "activation": 787, "while": 788, "stay": 789, "cspsource": 790, "private": 791, "busy": 792, "roots": 793, "outside": 794, "immediately": 795, "viewcolumn": 796, "receive": 797, "workspace_mcp_config_file": 798, "readmcpusage": 799, "into": 800, "searchhistory": 801, "guards": 802, "disk": 803, "preparing": 804, "scripts": 805, "mcpusage": 806, "lastgraphfileuri": 807, "instantly": 808, "spin": 809, "calls": 810, "fullgraph": 811, "did": 812, "generation": 813, "guaranteed": 814, "until": 815, "exist": 816, "1334": 817, "below": 818, "refreshmcpusage": 819, "again": 820, "127": 821, "appears": 822, "one": 823, "pinned": 824, "once": 825, "lastservergraphurl": 826, "copies": 827, "resource": 828, "mcpconfigwatcher": 829, "webviewpanel": 830, "capture": 831, "executecommand": 832, "completes": 833, "configpattern": 834, "leave": 835, "adoption": 836, "getfullgraphhtml": 837, "fallback": 838, "silently": 839, "opened": 840, "reload": 841, "postsearchhistory": 842, "refreshing": 843, "here": 844, "copying": 845, "sidepanel": 846, "options": 847, "falls": 848, "rest": 849, "system": 850, "currently": 851, "gethtml": 852, "loaded": 853, "leftover": 854, "workbench": 855, "execute": 856, "posted": 857, "localanalysisresultfileuri": 858, "recovery": 859, "resolves": 860, "ondiddelete": 861, "graphpanel": 862, "host": 863, "beside": 864, "still": 865, "capturesessionstartgitref": 866, "ondiddispose": 867, "after": 868, "uris": 869, "1812": 870, "1809": 871, "2397": 872, "2393": 873, "2442": 874, "scrollheight": 875, "msg": 876, "loc": 877, "child": 878, "classname": 879, "listener": 880, "openfile": 881, "el": 882, "q": 883, "span": 884, "messages": 885, "appendchild": 886, "scrolltop": 887, "height": 888, "errel": 889, "postmessage": 890, "addeventlistener": 891, "scroll": 892, "foreach": 893, "event": 894, "graphable": 895, "rendersearchresult": 896, "graphforresult": 897, "wrapper": 898, "answer": 899, "r": 900, "each": 901, "2399": 902, "top": 903}, "idf": [1.0, 1.0, 1.0, 1.0, 1.0, 1.0, 1.0, 1.0, 1.0, 1.0, 1.0, 1.0, 1.0, 1.0, 1.0, 1.1823215567939547, 1.1823215567939547, 1.2876820724517808, 1.4054651081081644, 1.4054651081081644, 1.4054651081081644, 1.538996500732687, 1.538996500732687, 1.538996500732687, 1.538996500732687, 1.538996500732687, 1.538996500732687, 1.538996500732687, 1.6931471805599454, 1.6931471805599454, 1.6931471805599454, 1.6931471805599454, 1.6931471805599454, 1.6931471805599454, 1.6931471805599454, 1.6931471805599454, 1.6931471805599454, 1.6931471805599454, 1.8754687373538999, 1.8754687373538999, 1.8754687373538999, 1.8754687373538999, 1.8754687373538999, 1.8754687373538999, 1.8754687373538999, 1.8754687373538999, 1.8754687373538999, 1.8754687373538999, 1.8754687373538999, 1.8754687373538999, 1.8754687373538999, 1.8754687373538999, 1.8754687373538999, 1.8754687373538999, 1.8754687373538999, 1.8754687373538999, 1.8754687373538999, 1.8754687373538999, 1.8754687373538999, 1.8754687373538999, 1.8754687373538999, 1.8754687373538999, 1.8754687373538999, 1.8754687373538999, 1.8754687373538999, 1.8754687373538999, 1.8754687373538999, 2.09861228866811, 2.09861228866811, 2.09861228866811, 2.09861228866811, 2.09861228866811, 2.09861228866811, 2.09861228866811, 2.09861228866811, 2.09861228866811, 2.09861228866811, 2.09861228866811, 2.09861228866811, 2.09861228866811, 2.09861228866811, 2.09861228866811, 2.09861228866811, 2.09861228866811, 2.09861228866811, 2.09861228866811, 2.09861228866811, 2.09861228866811, 2.09861228866811, 2.09861228866811, 2.09861228866811, 2.09861228866811, 2.09861228866811, 2.09861228866811, 2.09861228866811, 2.09861228866811, 2.09861228866811, 2.09861228866811, 2.09861228866811, 2.09861228866811, 2.09861228866811, 2.09861228866811, 2.09861228866811, 2.09861228866811, 2.09861228866811, 2.09861228866811, 2.09861228866811, 2.09861228866811, 2.09861228866811, 2.09861228866811, 2.09861228866811, 2.09861228866811, 2.09861228866811, 2.09861228866811, 2.09861228866811, 2.09861228866811, 2.09861228866811, 2.09861228866811, 2.09861228866811, 2.09861228866811, 2.09861228866811, 2.09861228866811, 2.09861228866811, 2.09861228866811, 2.09861228866811, 2.386294361119891, 2.386294361119891, 2.386294361119891, 2.386294361119891, 2.386294361119891, 2.386294361119891, 2.386294361119891, 2.386294361119891, 2.386294361119891, 2.386294361119891, 2.386294361119891, 2.386294361119891, 2.386294361119891, 2.386294361119891, 2.386294361119891, 2.386294361119891, 2.386294361119891, 2.386294361119891, 2.386294361119891, 2.386294361119891, 2.386294361119891, 2.386294361119891, 2.386294361119891, 2.386294361119891, 2.386294361119891, 2.386294361119891, 2.386294361119891, 2.386294361119891, 2.386294361119891, 2.386294361119891, 2.386294361119891, 2.386294361119891, 2.386294361119891, 2.386294361119891, 2.386294361119891, 2.386294361119891, 2.386294361119891, 2.386294361119891, 2.386294361119891, 2.386294361119891, 2.386294361119891, 2.386294361119891, 2.386294361119891, 2.386294361119891, 2.386294361119891, 2.386294361119891, 2.386294361119891, 2.386294361119891, 2.386294361119891, 2.386294361119891, 2.386294361119891, 2.386294361119891, 2.386294361119891, 2.386294361119891, 2.386294361119891, 2.386294361119891, 2.386294361119891, 2.386294361119891, 2.386294361119891, 2.386294361119891, 2.386294361119891, 2.386294361119891, 2.386294361119891, 2.386294361119891, 2.386294361119891, 2.386294361119891, 2.386294361119891, 2.386294361119891, 2.386294361119891, 2.386294361119891, 2.386294361119891, 2.386294361119891, 2.386294361119891, 2.386294361119891, 2.386294361119891, 2.386294361119891, 2.386294361119891, 2.386294361119891, 2.386294361119891, 2.386294361119891, 2.386294361119891, 2.386294361119891, 2.386294361119891, 2.386294361119891, 2.386294361119891, 2.386294361119891, 2.386294361119891, 2.386294361119891, 2.386294361119891, 2.386294361119891, 2.386294361119891, 2.386294361119891, 2.386294361119891, 2.386294361119891, 2.386294361119891, 2.386294361119891, 2.386294361119891, 2.386294361119891, 2.386294361119891, 2.386294361119891, 2.386294361119891, 2.386294361119891, 2.386294361119891, 2.386294361119891, 2.386294361119891, 2.386294361119891, 2.386294361119891, 2.386294361119891, 2.386294361119891, 2.386294361119891, 2.386294361119891, 2.386294361119891, 2.386294361119891, 2.386294361119891, 2.386294361119891, 2.386294361119891, 2.386294361119891, 2.386294361119891, 2.386294361119891, 2.386294361119891, 2.386294361119891, 2.386294361119891, 2.386294361119891, 2.386294361119891, 2.386294361119891, 2.386294361119891, 2.386294361119891, 2.386294361119891, 2.386294361119891, 2.386294361119891, 2.386294361119891, 2.386294361119891, 2.386294361119891, 2.386294361119891, 2.386294361119891, 2.386294361119891, 2.386294361119891, 2.386294361119891, 2.386294361119891, 2.386294361119891, 2.386294361119891, 2.386294361119891, 2.386294361119891, 2.386294361119891, 2.386294361119891, 2.386294361119891, 2.386294361119891, 2.386294361119891, 2.386294361119891, 2.386294361119891, 2.386294361119891, 2.386294361119891, 2.386294361119891, 2.386294361119891, 2.386294361119891, 2.386294361119891, 2.386294361119891, 2.386294361119891, 2.386294361119891, 2.386294361119891, 2.386294361119891, 2.386294361119891, 2.386294361119891, 2.386294361119891, 2.386294361119891, 2.386294361119891, 2.386294361119891, 2.386294361119891, 2.386294361119891, 2.386294361119891, 2.386294361119891, 2.386294361119891, 2.386294361119891, 2.386294361119891, 2.791759469228055, 2.791759469228055, 2.791759469228055, 2.791759469228055, 2.791759469228055, 2.791759469228055, 2.791759469228055, 2.791759469228055, 2.791759469228055, 2.791759469228055, 2.791759469228055, 2.791759469228055, 2.791759469228055, 2.791759469228055, 2.791759469228055, 2.791759469228055, 2.791759469228055, 2.791759469228055, 2.791759469228055, 2.791759469228055, 2.791759469228055, 2.791759469228055, 2.791759469228055, 2.791759469228055, 2.791759469228055, 2.791759469228055, 2.791759469228055, 2.791759469228055, 2.791759469228055, 2.791759469228055, 2.791759469228055, 2.791759469228055, 2.791759469228055, 2.791759469228055, 2.791759469228055, 2.791759469228055, 2.791759469228055, 2.791759469228055, 2.791759469228055, 2.791759469228055, 2.791759469228055, 2.791759469228055, 2.791759469228055, 2.791759469228055, 2.791759469228055, 2.791759469228055, 2.791759469228055, 2.791759469228055, 2.791759469228055, 2.791759469228055, 2.791759469228055, 2.791759469228055, 2.791759469228055, 2.791759469228055, 2.791759469228055, 2.791759469228055, 2.791759469228055, 2.791759469228055, 2.791759469228055, 2.791759469228055, 2.791759469228055, 2.791759469228055, 2.791759469228055, 2.791759469228055, 2.791759469228055, 2.791759469228055, 2.791759469228055, 2.791759469228055, 2.791759469228055, 2.791759469228055, 2.791759469228055, 2.791759469228055, 2.791759469228055, 2.791759469228055, 2.791759469228055, 2.791759469228055, 2.791759469228055, 2.791759469228055, 2.791759469228055, 2.791759469228055, 2.791759469228055, 2.791759469228055, 2.791759469228055, 2.791759469228055, 2.791759469228055, 2.791759469228055, 2.791759469228055, 2.791759469228055, 2.791759469228055, 2.791759469228055, 2.791759469228055, 2.791759469228055, 2.791759469228055, 2.791759469228055, 2.791759469228055, 2.791759469228055, 2.791759469228055, 2.791759469228055, 2.791759469228055, 2.791759469228055, 2.791759469228055, 2.791759469228055, 2.791759469228055, 2.791759469228055, 2.791759469228055, 2.791759469228055, 2.791759469228055, 2.791759469228055, 2.791759469228055, 2.791759469228055, 2.791759469228055, 2.791759469228055, 2.791759469228055, 2.791759469228055, 2.791759469228055, 2.791759469228055, 2.791759469228055, 2.791759469228055, 2.791759469228055, 2.791759469228055, 2.791759469228055, 2.791759469228055, 2.791759469228055, 2.791759469228055, 2.791759469228055, 2.791759469228055, 2.791759469228055, 2.791759469228055, 2.791759469228055, 2.791759469228055, 2.791759469228055, 2.791759469228055, 2.791759469228055, 2.791759469228055, 2.791759469228055, 2.791759469228055, 2.791759469228055, 2.791759469228055, 2.791759469228055, 2.791759469228055, 2.791759469228055, 2.791759469228055, 2.791759469228055, 2.791759469228055, 2.791759469228055, 2.791759469228055, 2.791759469228055, 2.791759469228055, 2.791759469228055, 2.791759469228055, 2.791759469228055, 2.791759469228055, 2.791759469228055, 2.791759469228055, 2.791759469228055, 2.791759469228055, 2.791759469228055, 2.791759469228055, 2.791759469228055, 2.791759469228055, 2.791759469228055, 2.791759469228055, 2.791759469228055, 2.791759469228055, 2.791759469228055, 2.791759469228055, 2.791759469228055, 2.791759469228055, 2.791759469228055, 2.791759469228055, 2.791759469228055, 2.791759469228055, 2.791759469228055, 2.791759469228055, 2.791759469228055, 2.791759469228055, 2.791759469228055, 2.791759469228055, 2.791759469228055, 2.791759469228055, 2.791759469228055, 2.791759469228055, 2.791759469228055, 2.791759469228055, 2.791759469228055, 2.791759469228055, 2.791759469228055, 2.791759469228055, 2.791759469228055, 2.791759469228055, 2.791759469228055, 2.791759469228055, 2.791759469228055, 2.791759469228055, 2.791759469228055, 2.791759469228055, 2.791759469228055, 2.791759469228055, 2.791759469228055, 2.791759469228055, 2.791759469228055, 2.791759469228055, 2.791759469228055, 2.791759469228055, 2.791759469228055, 2.791759469228055, 2.791759469228055, 2.791759469228055, 2.791759469228055, 2.791759469228055, 2.791759469228055, 2.791759469228055, 2.791759469228055, 2.791759469228055, 2.791759469228055, 2.791759469228055, 2.791759469228055, 2.791759469228055, 2.791759469228055, 2.791759469228055, 2.791759469228055, 2.791759469228055, 2.791759469228055, 2.791759469228055, 2.791759469228055, 2.791759469228055, 2.791759469228055, 2.791759469228055, 2.791759469228055, 2.791759469228055, 2.791759469228055, 2.791759469228055, 2.791759469228055, 2.791759469228055, 2.791759469228055, 2.791759469228055, 2.791759469228055, 2.791759469228055, 2.791759469228055, 2.791759469228055, 2.791759469228055, 2.791759469228055, 2.791759469228055, 2.791759469228055, 2.791759469228055, 2.791759469228055, 2.791759469228055, 2.791759469228055, 2.791759469228055, 2.791759469228055, 2.791759469228055, 2.791759469228055, 2.791759469228055, 2.791759469228055, 2.791759469228055, 2.791759469228055, 2.791759469228055, 2.791759469228055, 2.791759469228055, 2.791759469228055, 2.791759469228055, 2.791759469228055, 2.791759469228055, 2.791759469228055, 2.791759469228055, 2.791759469228055, 2.791759469228055, 2.791759469228055, 2.791759469228055, 2.791759469228055, 2.791759469228055, 2.791759469228055, 2.791759469228055, 2.791759469228055, 2.791759469228055, 2.791759469228055, 2.791759469228055, 2.791759469228055, 2.791759469228055, 2.791759469228055, 2.791759469228055, 2.791759469228055, 2.791759469228055, 2.791759469228055, 2.791759469228055, 2.791759469228055, 2.791759469228055, 2.791759469228055, 2.791759469228055, 2.791759469228055, 2.791759469228055, 2.791759469228055, 2.791759469228055, 2.791759469228055, 2.791759469228055, 2.791759469228055, 2.791759469228055, 2.791759469228055, 2.791759469228055, 2.791759469228055, 2.791759469228055, 2.791759469228055, 2.791759469228055, 2.791759469228055, 2.791759469228055, 2.791759469228055, 2.791759469228055, 2.791759469228055, 2.791759469228055, 2.791759469228055, 2.791759469228055, 2.791759469228055, 2.791759469228055, 2.791759469228055, 2.791759469228055, 2.791759469228055, 2.791759469228055, 2.791759469228055, 2.791759469228055, 2.791759469228055, 2.791759469228055, 2.791759469228055, 2.791759469228055, 2.791759469228055, 2.791759469228055, 2.791759469228055, 2.791759469228055, 2.791759469228055, 2.791759469228055, 2.791759469228055, 2.791759469228055, 2.791759469228055, 2.791759469228055, 2.791759469228055, 2.791759469228055, 2.791759469228055, 2.791759469228055, 2.791759469228055, 2.791759469228055, 2.791759469228055, 2.791759469228055, 2.791759469228055, 2.791759469228055, 2.791759469228055, 2.791759469228055, 2.791759469228055, 2.791759469228055, 2.791759469228055, 2.791759469228055, 2.791759469228055, 2.791759469228055, 2.791759469228055, 2.791759469228055, 2.791759469228055, 2.791759469228055, 2.791759469228055, 2.791759469228055, 2.791759469228055, 2.791759469228055, 2.791759469228055, 2.791759469228055, 2.791759469228055, 2.791759469228055, 2.791759469228055, 2.791759469228055, 2.791759469228055, 2.791759469228055, 2.791759469228055, 2.791759469228055, 2.791759469228055, 2.791759469228055, 2.791759469228055, 2.791759469228055, 2.791759469228055, 2.791759469228055, 2.791759469228055, 2.791759469228055, 2.791759469228055, 2.791759469228055, 2.791759469228055, 2.791759469228055, 2.791759469228055, 2.791759469228055, 2.791759469228055, 2.791759469228055, 2.791759469228055, 2.791759469228055, 2.791759469228055, 2.791759469228055, 2.791759469228055, 2.791759469228055, 2.791759469228055, 2.791759469228055, 2.791759469228055, 2.791759469228055, 2.791759469228055, 2.791759469228055, 2.791759469228055, 2.791759469228055, 2.791759469228055, 2.791759469228055, 2.791759469228055, 2.791759469228055, 2.791759469228055, 2.791759469228055, 2.791759469228055, 2.791759469228055, 2.791759469228055, 2.791759469228055, 2.791759469228055, 2.791759469228055, 2.791759469228055, 2.791759469228055, 2.791759469228055, 2.791759469228055, 2.791759469228055, 2.791759469228055, 2.791759469228055, 2.791759469228055, 2.791759469228055, 2.791759469228055, 2.791759469228055, 2.791759469228055, 2.791759469228055, 2.791759469228055, 2.791759469228055, 2.791759469228055, 2.791759469228055, 2.791759469228055, 2.791759469228055, 2.791759469228055, 2.791759469228055, 2.791759469228055, 2.791759469228055, 2.791759469228055, 2.791759469228055, 2.791759469228055, 2.791759469228055, 2.791759469228055, 2.791759469228055, 2.791759469228055, 2.791759469228055, 2.791759469228055, 2.791759469228055, 2.791759469228055, 2.791759469228055, 2.791759469228055, 2.791759469228055, 2.791759469228055, 2.791759469228055, 2.791759469228055, 2.791759469228055, 2.791759469228055, 2.791759469228055, 2.791759469228055, 2.791759469228055, 2.791759469228055, 2.791759469228055, 2.791759469228055, 2.791759469228055, 2.791759469228055, 2.791759469228055, 2.791759469228055, 2.791759469228055, 2.791759469228055, 2.791759469228055, 2.791759469228055, 2.791759469228055, 2.791759469228055, 2.791759469228055, 2.791759469228055, 2.791759469228055, 2.791759469228055, 2.791759469228055, 2.791759469228055, 2.791759469228055, 2.791759469228055, 2.791759469228055, 2.791759469228055, 2.791759469228055, 2.791759469228055, 2.791759469228055, 2.791759469228055, 2.791759469228055, 2.791759469228055, 2.791759469228055, 2.791759469228055, 2.791759469228055, 2.791759469228055, 2.791759469228055, 2.791759469228055, 2.791759469228055, 2.791759469228055, 2.791759469228055, 2.791759469228055, 2.791759469228055, 2.791759469228055, 2.791759469228055, 2.791759469228055, 2.791759469228055, 2.791759469228055, 2.791759469228055, 2.791759469228055, 2.791759469228055, 2.791759469228055, 2.791759469228055, 2.791759469228055, 2.791759469228055, 2.791759469228055, 2.791759469228055, 2.791759469228055, 2.791759469228055, 2.791759469228055, 2.791759469228055, 2.791759469228055, 2.791759469228055, 2.791759469228055, 2.791759469228055, 2.791759469228055, 2.791759469228055, 2.791759469228055, 2.791759469228055, 2.791759469228055, 2.791759469228055, 2.791759469228055, 2.791759469228055, 2.791759469228055, 2.791759469228055, 2.791759469228055, 2.791759469228055, 2.791759469228055, 2.791759469228055, 2.791759469228055, 2.791759469228055, 2.791759469228055, 2.791759469228055, 2.791759469228055, 2.791759469228055, 2.791759469228055, 2.791759469228055, 2.791759469228055, 2.791759469228055, 2.791759469228055, 2.791759469228055, 2.791759469228055, 2.791759469228055, 2.791759469228055, 2.791759469228055, 2.791759469228055, 2.791759469228055, 2.791759469228055, 2.791759469228055, 2.791759469228055, 2.791759469228055, 2.791759469228055, 2.791759469228055, 2.791759469228055, 2.791759469228055, 2.791759469228055, 2.791759469228055, 2.791759469228055, 2.791759469228055, 2.791759469228055, 2.791759469228055, 2.791759469228055, 2.791759469228055, 2.791759469228055, 2.791759469228055, 2.791759469228055, 2.791759469228055, 2.791759469228055, 2.791759469228055, 2.791759469228055, 2.791759469228055, 2.791759469228055, 2.791759469228055, 2.791759469228055, 2.791759469228055, 2.791759469228055, 2.791759469228055, 2.791759469228055, 2.791759469228055, 2.791759469228055, 2.791759469228055, 2.791759469228055, 2.791759469228055, 2.791759469228055, 2.791759469228055, 2.791759469228055, 2.791759469228055, 2.791759469228055, 2.791759469228055, 2.791759469228055, 2.791759469228055, 2.791759469228055, 2.791759469228055, 2.791759469228055, 2.791759469228055, 2.791759469228055, 2.791759469228055, 2.791759469228055, 2.791759469228055, 2.791759469228055, 2.791759469228055, 2.791759469228055]}, "graph_projector": {"dim": 128, "max_features": 8192, "prefix": "graph", "vocab": {"class:extension": 0, "pagerank_bucket:909": 1, "out_degree:0": 2, "in_degree:0": 3, "node:extension.activate": 4, "component:4": 5, "node:extension.deactivate": 6, "component:6": 7, "node:extension.check": 8, "component:5": 9, "node:extension.stopServer": 10, "component:10": 11, "component:2": 12, "node:extension.LocalCallgraphIndex": 13, "node:extension.ArtifactEntry": 14, "component:0": 15, "node:extension.NormalizedSearchResult": 16, "component:3": 17, "node:extension.GraphsViewProvider": 18, "component:1": 19, "node:extension.status": 20, "component:9": 21, "component:7": 22, "node:extension.escapeHtml": 23, "node:extension.renderSearchResult": 24, "component:8": 25}, "idf": [1.0, 1.0, 1.0, 1.0, 2.791759469228055, 2.791759469228055, 2.791759469228055, 2.791759469228055, 2.791759469228055, 2.791759469228055, 2.791759469228055, 2.791759469228055, 2.791759469228055, 2.791759469228055, 2.791759469228055, 2.791759469228055, 2.791759469228055, 2.791759469228055, 2.791759469228055, 2.791759469228055, 2.791759469228055, 2.791759469228055, 2.791759469228055, 2.791759469228055, 2.791759469228055, 2.791759469228055]}}